{
	"format_version": "1.8.0",
	"animations": {
		"falling": {
			"loop": true,
			"animation_length": 0.5,
			"bones": {
				"head": {
					"rotation": {
						"0.0": {
							"post": [-32.5, 0, 0],
							"lerp_mode": "catmullrom"
						},
						"0.125": {
							"post": [-33.83423, -19.50686, 15.76843],
							"lerp_mode": "catmullrom"
						},
						"0.25": {
							"post": [-34.84373, 13.5155, -11.38568],
							"lerp_mode": "catmullrom"
						},
						"0.375": {
							"post": [-32.33212, -5.87964, 4.66123],
							"lerp_mode": "catmullrom"
						},
						"0.5": {
							"post": [-32.88135, 3.90365, -3.14812],
							"lerp_mode": "catmullrom"
						}
					}
				},
				"body": {
					"rotation": {
						"0.0": {
							"post": [85, 0, 0],
							"lerp_mode": "catmullrom"
						},
						"0.125": {
							"post": [85.01895, 0.43516, 4.98108],
							"lerp_mode": "catmullrom"
						},
						"0.25": {
							"post": [85.07558, -0.86717, -9.96271],
							"lerp_mode": "catmullrom"
						},
						"0.375": {
							"post": [85.04252, 0.65179, 7.47175],
							"lerp_mode": "catmullrom"
						},
						"0.5": {
							"post": [85.01893, -0.43523, -4.98107],
							"lerp_mode": "catmullrom"
						}
					},
					"position": {
						"0.0": {
							"post": [0, -12, 0],
							"lerp_mode": "catmullrom"
						}
					}
				},
				"right_arm": {
					"rotation": {
						"0.0": {
							"post": [-202.5, 0, 0],
							"lerp_mode": "catmullrom"
						},
						"0.125": {
							"post": [-230, 0, 0],
							"lerp_mode": "catmullrom"
						},
						"0.25": {
							"post": [-185, 0, 0],
							"lerp_mode": "catmullrom"
						},
						"0.375": {
							"post": [-230, 0, 0],
							"lerp_mode": "catmullrom"
						},
						"0.5": {
							"post": [-200, 0, 0],
							"lerp_mode": "catmullrom"
						}
					}
				},
				"left_arm": {
					"rotation": {
						"0.0": {
							"post": [-227.5, 0, 0],
							"lerp_mode": "catmullrom"
						},
						"0.125": {
							"post": [-190, 0, 0],
							"lerp_mode": "catmullrom"
						},
						"0.25": {
							"post": [-233.64013, 5.88769, 6.10726],
							"lerp_mode": "catmullrom"
						},
						"0.375": {
							"post": [-190, 0, 0],
							"lerp_mode": "catmullrom"
						},
						"0.5": {
							"post": [-223.64013, 5.88769, 6.10726],
							"lerp_mode": "catmullrom"
						}
					}
				},
				"right_leg": {
					"rotation": {
						"0.0": {
							"post": [17.5, 0, 0],
							"lerp_mode": "catmullrom"
						},
						"0.125": {
							"post": [47.5, 0, 0],
							"lerp_mode": "catmullrom"
						},
						"0.25": {
							"post": [22.5, 0, 0],
							"lerp_mode": "catmullrom"
						},
						"0.375": {
							"post": [47.5, 0, 0],
							"lerp_mode": "catmullrom"
						},
						"0.5": {
							"post": [22.5, 0, 0],
							"lerp_mode": "catmullrom"
						}
					}
				},
				"left_leg": {
					"rotation": {
						"0.0": {
							"post": [60, 0, 0],
							"lerp_mode": "catmullrom"
						},
						"0.125": {
							"post": [32.5, 0, 0],
							"lerp_mode": "catmullrom"
						},
						"0.25": {
							"post": [65, 0, 0],
							"lerp_mode": "catmullrom"
						},
						"0.375": {
							"post": [32.5, 0, 0],
							"lerp_mode": "catmullrom"
						},
						"0.5": {
							"post": [65, 0, 0],
							"lerp_mode": "catmullrom"
						}
					}
				}
			}
		}
	},
	"geckolib_format_version": 2
}