{
	"format_version": "1.8.0",
	"animations": {
		"showed_up": {
			"animation_length": 0.1667,
			"bones": {
				"head": {
					"scale": {
						"0.0": {
							"post": {
								"vector": [0, 0, 0]
							},
							"lerp_mode": "catmullrom"
						},
						"0.0833": {
							"post": {
								"vector": [1.2, 1.2, 1.2]
							},
							"lerp_mode": "catmullrom"
						},
						"0.1667": {
							"post": {
								"vector": [1, 1, 1]
							},
							"lerp_mode": "catmullrom"
						}
					}
				}
			}
		},
		"idle": {
			"loop": true,
			"animation_length": 0.125,
			"bones": {
				"head": {
					"position": {
						"0.0": {
							"vector": [0, 0, 0]
						},
						"0.0417": {
							"vector": [-1, 0, 0]
						},
						"0.0833": {
							"vector": [1, 0, 0]
						},
						"0.125": {
							"vector": [0, 0, 0]
						}
					}
				}
			}
		},
		"close": {
			"loop": "hold_on_last_frame",
			"animation_length": 0.1667,
			"bones": {
				"head": {
					"scale": {
						"0.0": {
							"post": {
								"vector": [1, 1, 1]
							},
							"lerp_mode": "catmullrom"
						},
						"0.0833": {
							"post": {
								"vector": [1.2, 1.2, 1.2]
							},
							"lerp_mode": "catmullrom"
						},
						"0.1667": {
							"post": {
								"vector": [0, 0, 0]
							},
							"lerp_mode": "catmullrom"
						}
					}
				}
			}
		}
	}
}