{
    "pools": [
        {
            "rolls": 1,
            "entries": [
                {
                    "type": "minecraft:item",
                    "name": "welcometomyworld:fallen_hammer",
                    "weight": 5
                },
                {
                    "type": "minecraft:item",
                    "name": "minecraft:diamond_sword",
                    "weight": 10,
                    "functions": [
                        {
                            "function": "minecraft:enchant_randomly"
                        }
                    ]
                },
                {
                    "type": "minecraft:item",
                    "name": "minecraft:diamond_axe",
                    "weight": 10,
                    "functions": [
                        {
                            "function": "minecraft:enchant_randomly"
                        }
                    ]
                }
            ]
        },
        {
            "rolls": {
                "min": 2,
                "max": 4
            },
            "entries": [
                {
                    "type": "minecraft:item",
                    "name": "minecraft:iron_ingot",
                    "weight": 20,
                    "functions": [
                        {
                            "function": "minecraft:set_count",
                            "count": {
                                "min": 1,
                                "max": 5
                            }
                        }
                    ]
                },
                {
                    "type": "minecraft:item",
                    "name": "minecraft:gold_ingot",
                    "weight": 15,
                    "functions": [
                        {
                            "function": "minecraft:set_count",
                            "count": {
                                "min": 1,
                                "max": 3
                            }
                        }
                    ]
                },
                {
                    "type": "minecraft:item",
                    "name": "minecraft:diamond",
                    "weight": 8,
                    "functions": [
                        {
                            "function": "minecraft:set_count",
                            "count": {
                                "min": 1,
                                "max": 2
                            }
                        }
                    ]
                },
                {
                    "type": "minecraft:item",
                    "name": "welcometomyworld:ancient_fragment",
                    "weight": 10
                }
            ]
        },
        {
            "rolls": 1,
            "entries": [
                {
                    "type": "minecraft:item",
                    "name": "welcometomyworld:power_talisman",
                    "weight": 5
                },
                {
                    "type": "minecraft:item",
                    "name": "welcometomyworld:speed_talisman",
                    "weight": 5
                },
                {
                    "type": "minecraft:item",
                    "name": "welcometomyworld:life_talisman",
                    "weight": 5
                },
                {
                    "type": "minecraft:item",
                    "name": "welcometomyworld:resistance_talisman",
                    "weight": 5
                },
                {
                    "type": "minecraft:item",
                    "name": "welcometomyworld:creeper_talisman",
                    "weight": 2
                }
            ]
        },
        {
            "rolls": {
                "min": 1,
                "max": 3
            },
            "entries": [
                {
                    "type": "minecraft:item",
                    "name": "welcometomyworld:repair_knowledge",
                    "weight": 10
                },
                {
                    "type": "minecraft:item",
                    "name": "welcometomyworld:repair_talisman_iron",
                    "weight": 10
                },
                {
                    "type": "minecraft:item",
                    "name": "welcometomyworld:repair_talisman_gold",
                    "weight": 5
                }
            ]
        },
        {
            "rolls": 3,
            "entries": [
                {
                    "type": "minecraft:item",
                    "name": "minecraft:bone",
                    "weight": 20,
                    "functions": [
                        {
                            "function": "minecraft:set_count",
                            "count": {
                                "min": 4,
                                "max": 12
                            }
                        }
                    ]
                },
                {
                    "type": "minecraft:item",
                    "name": "minecraft:cobweb",
                    "weight": 15,
                    "functions": [
                        {
                            "function": "minecraft:set_count",
                            "count": {
                                "min": 1,
                                "max": 8
                            }
                        }
                    ]
                },
                {
                    "type": "minecraft:item",
                    "name": "minecraft:soul_campfire",
                    "weight": 10,
                    "functions": [
                        {
                            "function": "minecraft:set_count",
                            "count": 1
                        }
                    ]
                }
            ]
        }
    ]
}